LICENSE.txt
README.md
setup.cfg
setup.py
django_rtk_green/__init__.py
django_rtk_green/apps.py
django_rtk_green/backends.py
django_rtk_green/validators.py
django_rtk_green.egg-info/PKG-INFO
django_rtk_green.egg-info/SOURCES.txt
django_rtk_green.egg-info/dependency_links.txt
django_rtk_green.egg-info/not-zip-safe
django_rtk_green.egg-info/requires.txt
django_rtk_green.egg-info/top_level.txt
django_rtk_green/mutations/__init__.py
django_rtk_green/queries/__init__.py