Metadata-Version: 2.1
Name: django-rtk-green
Version: 0.4.0
Summary: Extension of django-rtk that combines django-rtk-later, django-rtk-password and django-rtk-magic-link
Home-page: https://github.com/mnieber/django-rtk-home/blob/main/django-rtk-green/README.md
Author: Maarten Nieber
Author-email: hallomaarten@yahoo.com
License: MIT
Platform: UNKNOWN
Requires-Python: >=3.6
